setup.cfg
setup.py
scTDA/__init__.py
scTDA/main.py
scTDA.egg-info/PKG-INFO
scTDA.egg-info/SOURCES.txt
scTDA.egg-info/dependency_links.txt
scTDA.egg-info/not-zip-safe
scTDA.egg-info/requires.txt
scTDA.egg-info/top_level.txt