Metadata-Version: 1.0
Name: scTDA
Version: 0.97
Summary: An object oriented python library for topological data analysis of high-throughput single-cell RNA-seq data
Home-page: https://github.com/pcamara/scTDA
Author: Pablo G. Camara
Author-email: pablo.g.camara@gmail.com
License: GPL-3.0
Platform: UNKNOWN
